Metadata-Version: 2.1
Name: CodeWarsLeaderBoard
Version: 0.2
Summary: Runs a web scraper in a background for getting leader board details for 500 top users of codewars.com
Home-page: https://github.com/urosjevremovic/CodeWarsLeaderBoard
Author: Uros Jevremovic
Author-email: jevremovic.uros91@gmail.com
License: MIT
Platform: UNKNOWN
